bst/__init__.py
bst/bst.py
linked_list/__init__.py
linked_list/doubly_linked_list.py
linked_list/singly_linked_list.py
tests/__init__.py
tests/test_bst.py
tests/test_doubly_linked_list.py
tests/test_singly_linked_list.py
ds_collections-1.0.0.dist-info/LICENSE
ds_collections-1.0.0.dist-info/METADATA
ds_collections-1.0.0.dist-info/WHEEL
ds_collections-1.0.0.dist-info/top_level.txt
ds_collections-1.0.0.dist-info/RECORD
